pico_ioc/__init__.py
pico_ioc/_version.py
pico_ioc/analysis.py
pico_ioc/aop.py
pico_ioc/api.py
pico_ioc/component_scanner.py
pico_ioc/config_builder.py
pico_ioc/config_registrar.py
pico_ioc/config_runtime.py
pico_ioc/constants.py
pico_ioc/container.py
pico_ioc/decorators.py
pico_ioc/dependency_validator.py
pico_ioc/event_bus.py
pico_ioc/exceptions.py
pico_ioc/factory.py
pico_ioc/locator.py
pico_ioc/provider_selector.py
pico_ioc/registrar.py
pico_ioc/scope.py
pico_ioc-2.1.2.dist-info/licenses/LICENSE
pico_ioc-2.1.2.dist-info/METADATA
pico_ioc-2.1.2.dist-info/WHEEL
pico_ioc-2.1.2.dist-info/top_level.txt
pico_ioc-2.1.2.dist-info/RECORD
