Metadata-Version: 2.4
Name: pico-ioc
Version: 2.1.2
Summary: A minimalist, zero-dependency Inversion of Control (IoC) container for Python.
Author-email: David Perez Cabrera <dperezcabrera@gmail.com>
License: MIT License
Project-URL: Homepage, https://github.com/dperezcabrera/pico-ioc
Project-URL: Repository, https://github.com/dperezcabrera/pico-ioc
Project-URL: Issue Tracker, https://github.com/dperezcabrera/pico-ioc/issues
Keywords: ioc,di,dependency injection,inversion of control,decorator
Classifier: Development Status :: 4 - Beta
Classifier: Programming Language :: Python :: 3
Classifier: Programming Language :: Python :: 3 :: Only
Classifier: Programming Language :: Python :: 3.10
Classifier: Programming Language :: Python :: 3.11
Classifier: Programming Language :: Python :: 3.12
Classifier: Programming Language :: Python :: 3.13
Classifier: Programming Language :: Python :: 3.14
Classifier: License :: OSI Approved :: MIT License
Classifier: Operating System :: OS Independent
Requires-Python: >=3.10
License-File: LICENSE
Provides-Extra: yaml
Requires-Dist: PyYAML; extra == "yaml"
Provides-Extra: graphviz
Requires-Dist: graphviz; extra == "graphviz"
Dynamic: license-file
